HISTORY.rst
LICENSE
MANIFEST.in
README.rst
expak.py
setup.py
expak.egg-info/PKG-INFO
expak.egg-info/SOURCES.txt
expak.egg-info/dependency_links.txt
expak.egg-info/entry_points.txt
expak.egg-info/top_level.txt
expak.egg-info/zip-safe
test/test_expak.py
test/input/pak_a.pak
test/input/pak_b.pak
test/input/this_is_not_a.pak
test/input/tiny_bad.pack
test/input/truncated.pak
test/input/files/data_a
test/input/files/data_b
test/input/files/doc_a.txt
test/input/files/doc_b.txt
test/input/files/subdir_1/subdir_2/data_a
test/input/files/subdir_1/subdir_2/data_b
test/input/files/subdir_1/subdir_2/doc_a.txt
test/input/files/subdir_1/subdir_2/doc_b.txt
test/input/mangled_files/data_a
test/input/mangled_files/data_b
test/input/mangled_files/doc_a.txt
test/input/mangled_files/doc_b.txt
test/input/mangled_files/subdir_1/subdir_2/data_a
test/input/mangled_files/subdir_1/subdir_2/data_b
test/input/mangled_files/subdir_1/subdir_2/doc_a.txt
test/input/mangled_files/subdir_1/subdir_2/doc_b.txt