Metadata-Version: 1.0
Name: expak
Version: 1.0
Summary: Extract and process resources from Quake-style pak files
Home-page: http://github.com/neogeographica/expak
Author: Joel Baxter
Author-email: joel.baxter@neogeographica.com
License: GPLv3
Platform: any
Classifier: Development Status :: 5 - Production/Stable
Classifier: Environment :: Console
Classifier: Intended Audience :: Developers
Classifier: License :: OSI Approved :: GNU General Public License v3 (GPLv3)
Classifier: Natural Language :: English
Classifier: Operating System :: OS Independent
Classifier: Programming Language :: Python
Classifier: Programming Language :: Python :: 2.6
Classifier: Programming Language :: Python :: 2.7
Classifier: Topic :: Software Development :: Libraries :: Python Modules
Classifier: Topic :: Utilities
